pyutilkit/__init__.py
pyutilkit/__version__.py
pyutilkit/classes.py
pyutilkit/data/__init__.py
pyutilkit/data/timezones.py
pyutilkit/date_utils.py
pyutilkit/files.py
pyutilkit/py.typed
pyutilkit/subprocess.py
pyutilkit/term.py
pyutilkit/timing.py
pyutilkit-0.11.0.dist-info/LICENSE.md
pyutilkit-0.11.0.dist-info/METADATA
pyutilkit-0.11.0.dist-info/WHEEL
pyutilkit-0.11.0.dist-info/RECORD
