Metadata-Version: 2.3
Name: pyutilkit
Version: 0.11.0
Summary: python's missing batteries
Home-page: https://pyutilkit.readthedocs.io/en/stable/
License: BSD-3-Clause
Keywords: utils
Author: Stephanos Kuma
Author-email: "Stephanos Kuma" <stephanos@kuma.ai>
Requires-Python: >=3.10
Classifier: Development Status :: 4 - Beta
Classifier: License :: OSI Approved :: BSD License
Classifier: Operating System :: OS Independent
Classifier: Programming Language :: Python :: 3 :: Only
Requires-Dist: tzdata ; os_name == 'nt'
Project-URL: Documentation, https://pyutilkit.readthedocs.io/en/stable/
Project-URL: Repository, https://github.com/spapanik/pyutilkit
